foliant/preprocessors/imagemagick.py
foliantcontrib.imagemagick-1.0.2.dist-info/LICENSE
foliantcontrib.imagemagick-1.0.2.dist-info/METADATA
foliantcontrib.imagemagick-1.0.2.dist-info/WHEEL
foliantcontrib.imagemagick-1.0.2.dist-info/top_level.txt
foliantcontrib.imagemagick-1.0.2.dist-info/RECORD
